<?xml version="1.0" encoding="UTF-8"?>
<!DOCTYPE mapper PUBLIC "-//mybatis.org//DTD Mapper 3.0//EN" "http://mybatis.org/dtd/mybatis-3-mapper.dtd">
<!--
  automatically generated OutBoundGoodEntity Mapper xml
-->
<mapper namespace="com.weitest.wms.repository.entities.OutBoundGoodEntityMapper">
    <resultMap id="BaseResultMap" type="com.weitest.wms.domain.entities.OutBoundGoodEntity">
        <id column="id" jdbcType="BIGINT" property="id" />
        <result column="outboundOrderId" jdbcType="BIGINT" property="outbound_order_id" />
        <result column="name" jdbcType="VARCHAR" property="name" />
        <result column="quantity" jdbcType="BIGINT" property="quantity" />
        <result column="unit" jdbcType="VARCHAR" property="unit" />
        <result column="status" jdbcType="VARCHAR" property="status" />
        <result column="weight" jdbcType="DECIMAL" property="weight" />
    </resultMap>

    <!--
       ###################################################
       ######### mysql
       ###################################################
     -->
    <insert id="insert" parameterType="com.weitest.wms.domain.entities.OutBoundGoodEntity"  keyProperty="id" useGeneratedKeys="true">
        INSERT INTO `OutBoundGood` (
            `outboundOrderId`
            ,`name`
            ,`quantity`
            ,`unit`
            ,`status`
            ,`weight`
        )
        VALUES (
            #{outbound_order_id,jdbcType=BIGINT}
            ,#{name,jdbcType=VARCHAR}
            ,#{quantity,jdbcType=BIGINT}
            ,#{unit,jdbcType=VARCHAR}
            ,#{status,jdbcType=VARCHAR}
            ,#{weight,jdbcType=DECIMAL}
        )
    </insert>

    <insert id="batchInsert"  parameterType="java.util.List" keyProperty="id" useGeneratedKeys="true">
        INSERT INTO `OutBoundGood` (
            `outboundOrderId`
            ,`name`
            ,`quantity`
            ,`unit`
            ,`status`
            ,`weight`
        )
        VALUES
        <foreach collection="list" item="item" index="index" separator=",">
        (
            #{item.outbound_order_id,jdbcType=BIGINT}
            ,#{item.name,jdbcType=VARCHAR}
            ,#{item.quantity,jdbcType=BIGINT}
            ,#{item.unit,jdbcType=VARCHAR}
            ,#{item.status,jdbcType=VARCHAR}
            ,#{item.weight,jdbcType=DECIMAL}
         )
        </foreach>
    </insert>

    <update id="update" parameterType="com.weitest.wms.domain.entities.OutBoundGoodEntity" >
        UPDATE `OutBoundGood`
        <set>
            <if test="updateFields == null or updateFields.contains('outbound_order_id')">`outboundOrderId` = #{bean.outbound_order_id,jdbcType=BIGINT},</if>
            <if test="updateFields == null or updateFields.contains('name')">`name` = #{bean.name,jdbcType=VARCHAR},</if>
            <if test="updateFields == null or updateFields.contains('quantity')">`quantity` = #{bean.quantity,jdbcType=BIGINT},</if>
            <if test="updateFields == null or updateFields.contains('unit')">`unit` = #{bean.unit,jdbcType=VARCHAR},</if>
            <if test="updateFields == null or updateFields.contains('status')">`status` = #{bean.status,jdbcType=VARCHAR},</if>
            <if test="updateFields == null or updateFields.contains('weight')">`weight` = #{bean.weight,jdbcType=DECIMAL},</if>
        </set>
        where `id` = #{bean.id}
    </update>

    <!-- todo -->
    <update id="batchUpdate" parameterType="com.weitest.wms.domain.entities.OutBoundGoodEntity" >
        UPDATE `OutBoundGood`
        <set>
            <if test="updateFields == null or updateFields.contains('outbound_order_id')">`outboundOrderId` = #{bean.outbound_order_id,jdbcType=BIGINT},</if>
            <if test="updateFields == null or updateFields.contains('name')">`name` = #{bean.name,jdbcType=VARCHAR},</if>
            <if test="updateFields == null or updateFields.contains('quantity')">`quantity` = #{bean.quantity,jdbcType=BIGINT},</if>
            <if test="updateFields == null or updateFields.contains('unit')">`unit` = #{bean.unit,jdbcType=VARCHAR},</if>
            <if test="updateFields == null or updateFields.contains('status')">`status` = #{bean.status,jdbcType=VARCHAR},</if>
            <if test="updateFields == null or updateFields.contains('weight')">`weight` = #{bean.weight,jdbcType=DECIMAL},</if>
        </set>
        where `id` = #{bean.id}
    </update>


    <delete id="delete" parameterType="java.lang.Long" >
        DELETE FROM `OutBoundGood` where `id` = #{id}
    </delete>


    <delete id="batchDelete" >
        DELETE FROM `OutBoundGood` where `id` in
        <foreach collection="list" item="pkValueItem" index="index"  separator="," open="(" close=")">
            #{pkValueItem}
        </foreach>
    </delete>

    <delete id="deleteReference">
        DELETE FROM `OutBoundGood`
        <where>
            <choose>
                <when test="property == 'id'">
                    AND `id` = #{value, jdbcType=BIGINT}
                </when>
                <when test="property == 'outbound_order_id'">
                    AND `outboundOrderId` = #{value, jdbcType=BIGINT}
                </when>
                <when test="property == 'name'">
                    AND `name` = #{value, jdbcType=VARCHAR}
                </when>
                <when test="property == 'quantity'">
                    AND `quantity` = #{value, jdbcType=BIGINT}
                </when>
                <when test="property == 'unit'">
                    AND `unit` = #{value, jdbcType=VARCHAR}
                </when>
                <when test="property == 'status'">
                    AND `status` = #{value, jdbcType=VARCHAR}
                </when>
                <when test="property == 'weight'">
                    AND `weight` = #{value, jdbcType=DECIMAL}
                </when>
                <otherwise>
                    MUST BE ERROR
                </otherwise>
            </choose>
        </where>
    </delete>

    <select id="existReference" resultType="java.lang.Long" >
        select `id` from `OutBoundGood` 
        <where>
            <choose>
                <when test="property == 'id'">
                    AND `id` = #{value, jdbcType=BIGINT}
                </when>
                <when test="property == 'outbound_order_id'">
                    AND `outboundOrderId` = #{value, jdbcType=BIGINT}
                </when>
                <when test="property == 'name'">
                    AND `name` = #{value, jdbcType=VARCHAR}
                </when>
                <when test="property == 'quantity'">
                    AND `quantity` = #{value, jdbcType=BIGINT}
                </when>
                <when test="property == 'unit'">
                    AND `unit` = #{value, jdbcType=VARCHAR}
                </when>
                <when test="property == 'status'">
                    AND `status` = #{value, jdbcType=VARCHAR}
                </when>
                <when test="property == 'weight'">
                    AND `weight` = #{value, jdbcType=DECIMAL}
                </when>
                <otherwise>
                    MUST BE ERROR
                </otherwise>
            </choose>
        </where>
         LIMIT 1
    </select>


    <select id="selectOne" resultMap="BaseResultMap" >
        select * from `OutBoundGood` where `id`=#{id}
    </select>

    <select id="selectList" parameterType="com.weitest.wms.service.dto.filters.AbstractQueryFilter" resultMap="BaseResultMap" >
        select * from `OutBoundGood`
        <where>
            ${filter.sql("mysql")}
        </where>
    </select>

    <select id="count" parameterType="com.weitest.wms.service.dto.filters.AbstractQueryFilter" resultType="java.lang.Integer" >
        select count(1) from `OutBoundGood`
        <where>
            ${filter.sql("mysql")}
        </where>
    </select>

    <insert id="createOrUpdate" parameterType="com.weitest.wms.domain.entities.OutBoundGoodEntity">
        INSERT INTO `OutBoundGood` (
            `id`
            ,`outboundOrderId`
            ,`name`
            ,`quantity`
            ,`unit`
            ,`status`
            ,`weight`
        )
        VALUES (
            #{id,jdbcType=BIGINT}
            ,#{outbound_order_id,jdbcType=BIGINT}
            ,#{name,jdbcType=VARCHAR}
            ,#{quantity,jdbcType=BIGINT}
            ,#{unit,jdbcType=VARCHAR}
            ,#{status,jdbcType=VARCHAR}
            ,#{weight,jdbcType=DECIMAL}
        )
    </insert>


    <update id="updateBy">
        UPDATE `OutBoundGood`
        <set>
        <if test="updateFields == null or updateFields.contains('outbound_order_id')">`outboundOrderId` = #{bean.outbound_order_id,jdbcType=BIGINT},</if>
        <if test="updateFields == null or updateFields.contains('name')">`name` = #{bean.name,jdbcType=VARCHAR},</if>
        <if test="updateFields == null or updateFields.contains('quantity')">`quantity` = #{bean.quantity,jdbcType=BIGINT},</if>
        <if test="updateFields == null or updateFields.contains('unit')">`unit` = #{bean.unit,jdbcType=VARCHAR},</if>
        <if test="updateFields == null or updateFields.contains('status')">`status` = #{bean.status,jdbcType=VARCHAR},</if>
        <if test="updateFields == null or updateFields.contains('weight')">`weight` = #{bean.weight,jdbcType=DECIMAL},</if>
        </set>
        where ${filter.sql("mysql")}
    </update>

    <delete id="deleteBy" parameterType="com.weitest.wms.service.dto.filters.AbstractQueryFilter">
        DELETE FROM `OutBoundGood` where ${filter.sql("mysql")}
    </delete>
</mapper>